yelllovkitten/TimeData.py
yelllovkitten/__init__.py
yelllovkitten/protection.py
yelllovkitten/text.py
yelllovkitten-0.0.11.3.dist-info/METADATA
yelllovkitten-0.0.11.3.dist-info/WHEEL
yelllovkitten-0.0.11.3.dist-info/licenses/LICENSE
yelllovkitten-0.0.11.3.dist-info/RECORD
