Metadata-Version: 2.4
Name: Yelllovkitten
Version: 0.0.11.3
Summary: Just a package
Project-URL: Homepage, https://t.me/yelllovkitten
Project-URL: Issues, https://t.me/yelllovkitten/1373
Author-email: yelllovkitten <yelllovkitten@gmail.com>
License-File: LICENSE
Classifier: License :: OSI Approved :: MIT License
Classifier: Operating System :: OS Independent
Classifier: Programming Language :: Python :: 3
Requires-Python: >=3.11
